bitarray/__init__.py
bitarray/_bitarray.c
bitarray/_bitarray.cp36-win_amd64.pyd
bitarray/_util.c
bitarray/_util.cp36-win_amd64.pyd
bitarray/test_bitarray.py
bitarray/test_util.py
bitarray/util.py
bitarray_hardbyte-1.6.2.dist-info/AUTHORS
bitarray_hardbyte-1.6.2.dist-info/LICENSE
bitarray_hardbyte-1.6.2.dist-info/METADATA
bitarray_hardbyte-1.6.2.dist-info/WHEEL
bitarray_hardbyte-1.6.2.dist-info/top_level.txt
bitarray_hardbyte-1.6.2.dist-info/RECORD
