Metadata-Version: 2.1
Name: bitarray-hardbyte
Version: 1.6.2
Summary: efficient arrays of booleans -- C extension
Home-page: https://github.com/ilanschnell/bitarray
Author: Ilan Schnell
Author-email: ilanschnell@gmail.com
License: PSF
Platform: UNKNOWN
Classifier: License :: OSI Approved :: Python Software Foundation License
Classifier: Development Status :: 5 - Production/Stable
Classifier: Intended Audience :: Developers
Classifier: Operating System :: OS Independent
Classifier: Programming Language :: C
Classifier: Programming Language :: Python :: 2
Classifier: Programming Language :: Python :: 2.7
Classifier: Programming Language :: Python :: 3
Classifier: Programming Language :: Python :: 3.5
Classifier: Programming Language :: Python :: 3.6
Classifier: Programming Language :: Python :: 3.7
Classifier: Programming Language :: Python :: 3.8
Classifier: Programming Language :: Python :: 3.9
Classifier: Topic :: Utilities
